lip_pps_run_manager/__init__.py
lip_pps_run_manager/__main__.py
lip_pps_run_manager/cli.py
lip_pps_run_manager/run_manager.py
lip_pps_run_manager/setup_manager.py
lip_pps_run_manager/telegram_reporter.py
lip_pps_run_manager/instruments/Keithley6487.py
lip_pps_run_manager/instruments/__init__.py
lip_pps_run_manager/instruments/functions.py
lip_pps_run_manager-0.3.0.dist-info/AUTHORS.rst
lip_pps_run_manager-0.3.0.dist-info/LICENSE
lip_pps_run_manager-0.3.0.dist-info/METADATA
lip_pps_run_manager-0.3.0.dist-info/WHEEL
lip_pps_run_manager-0.3.0.dist-info/entry_points.txt
lip_pps_run_manager-0.3.0.dist-info/top_level.txt
lip_pps_run_manager-0.3.0.dist-info/RECORD
