Metadata-Version: 2.1
Name: lip-pps-run-manager
Version: 0.3.0
Summary: Run Manager used in the LIP PPS software stack for handling data taking and analysis
Home-page: https://github.com/cbeiraod/LIP_PPS_Run_Manager
Author: Cristóvão B. da Cruz e Silva
Author-email: cbeiraod@cern.ch
License: MIT
Project-URL: Documentation, https://lip-pps-run-manager.readthedocs.io/
Project-URL: Changelog, https://lip-pps-run-manager.readthedocs.io/en/latest/changelog.html
Project-URL: Issue Tracker, https://github.com/cbeiraod/LIP_PPS_Run_Manager/issues
Platform: UNKNOWN
Classifier: Development Status :: 5 - Production/Stable
Classifier: Intended Audience :: Developers
Classifier: License :: OSI Approved :: MIT License
Classifier: Operating System :: Unix
Classifier: Operating System :: POSIX
Classifier: Operating System :: Microsoft :: Windows
Classifier: Programming Language :: Python
Classifier: Programming Language :: Python :: 3
Classifier: Programming Language :: Python :: 3 :: Only
Classifier: Programming Language :: Python :: 3.7
Classifier: Programming Language :: Python :: 3.8
Classifier: Programming Language :: Python :: 3.9
Classifier: Programming Language :: Python :: 3.10
Classifier: Programming Language :: Python :: 3.11
Classifier: Programming Language :: Python :: Implementation :: CPython
Classifier: Programming Language :: Python :: Implementation :: PyPy
Classifier: Topic :: Utilities
Requires-Python: >=3.7
License-File: LICENSE
License-File: AUTHORS.rst
Requires-Dist: requests
Requires-Dist: humanize
Requires-Dist: pyvisa
